{"songFilename":"anilog1seq-17b4b659d33-9211.json","songUrl":"http:\/\/ani-web.com\/anilog","songFeedbackWetMix":1,"songTitle":"[Beat] Drumz 'n Bazz","currentTime":1631889814.822422,"appVersion":"1.1.0","lastBank":0,"songFeedbackBrightness":0.79642540216445923,"songFeedbackAttenuate":0.83860898017883301,"songArtist":"ANI","patterns":[{"name":"","rows":[{"cc":"V64i00n30v73,,V64i02n30p2Cv6E,V64i06n35v69,V2Ci07n59v69"},{"cc":",,n--,n--"},{"cc":",,V64i02n30p54v10,V64i06n35v69"},{"cc":",,n--,n--"},{"cc":",V64i01n30v73,V64i02n30p2Bv49,V64i06n35v69"},{"cc":",,n--,n--"},{"cc":"V64i00n30v73,,V64i02n30p4Cv1A,V64i06n35v69"},{"cc":",,n--,n--"},{"cc":",,V64i02n30p2Cv55,V64i06n35v69"},{"cc":",,n--,n--"},{"cc":"V64i00n30v73,,V64i02n30p54v15,V64i06n35v69"},{"cc":",,n--,n--"},{"cc":",V64i01n30v73,V64i02n30p2Bv6B,V64i06n35v69"},{"cc":",,n--,n--"},{"cc":",,V64i02n30p4Cv1B,V64i06n35v69"},{"cc":",,n--,n--"},{"cc":"V64i00n30v73,,V64i02n30p2Cv6E,V64i06n35v69"},{"cc":",,n--,n--"},{"cc":",,V64i02n30p54v10,V64i06n35v69"},{"cc":",,n--,n--"},{"cc":",V64i01n30v73,V64i02n30p2Bv49,V64i06n35v69"},{"cc":",,n--,n--"},{"cc":"V64i00n30v73,,V64i02n30p4Cv1A,V64i06n35v69"},{"cc":",,n--,n--"},{"cc":",,V64i02n30p2Cv55,V64i06n35v69"},{"cc":",,n--,n--"},{"cc":"V64i00n30v73,,V64i02n30p54v15,V64i06n35v69"},{"cc":",,n--,n--"},{"cc":",V64i01n30v73,V64i02n30p2Bv6B,V64i06n38v62"},{"cc":",,n--,n--"},{"cc":",,V64i02n30p4Cv1B,V64i06n38v62"},{"cc":",,n--,n--"},{"cc":"V64i00n30v73,,V64i02n30p2Cv6E,V64i06n33v5D,V2Ci07n57v56"},{"cc":",,n--,n--"},{"cc":",,V64i02n30p54v10,V64i06n33v5D"},{"cc":",,n--,n--"},{"cc":",V64i01n30v73,V64i02n30p2Bv49,V64i06n33v5D"},{"cc":",,n--,n--"},{"cc":"V64i00n30v73,,V64i02n30p4Cv1A,V64i06n33v5D"},{"cc":",,n--,n--"},{"cc":",,V64i02n30p2Cv55,V64i06n33v5D"},{"cc":",,n--,n--"},{"cc":"V64i00n30v73,,V64i02n30p54v15,V64i06n33v5D"},{"cc":",,n--,n--"},{"cc":",V64i01n30v73,V64i02n30p2Bv6B,V64i06n33v5D"},{"cc":",,n--,n--"},{"cc":",,V64i02n30p4Cv1B,V64i06n33v5D"},{"cc":",,n--,n--"},{"cc":"V64i00n30v73,,V64i02n30p2Cv6E,V64i06n33v5D"},{"cc":",,n--,n--"},{"cc":",,V64i02n30p54v10,V64i06n33v5D"},{"cc":",,n--,n--"},{"cc":",V64i01n30v73,V64i02n30p2Bv49,V64i06n33v5D"},{"cc":",,n--,n--"},{"cc":"V64i00n30v73,,V64i02n30p4Cv1A,V64i06n33v5D"},{"cc":",,n--,n--"},{"cc":"V64i00n30v37,,V64i02n30p2Cv55,V64i06n33v5D"},{"cc":",,n--,n--"},{"cc":"V64i00n30v73,,V64i02n30p54v15,V64i06n33v5D"},{"cc":",,n--,n--"},{"cc":",V64i01n30v73,V64i02n30p2Bv6B,V64i06n37v66"},{"cc":",,n--,n--"},{"cc":",,V64i02n30p4Cv1B,V64i06n37v66"},{"cc":",,n--,n--"}]}],"songBpm":210,"songDescription":"Basic boom-chack!","appName":"ANILOG","songTrackAttributes":[{"v":1,"f":0,"m":false},{"m":false,"f":0.40000000596046448,"v":1},{"f":0,"v":1,"m":false},{"m":false,"v":1,"f":0},{"v":0.70575892925262451,"f":0,"m":false},{"m":false,"f":0,"v":1},{"v":1,"f":0,"m":false},{"v":1,"f":0,"m":false},{"v":1,"f":0,"m":false},{"m":false,"v":1,"f":0},{"f":0,"v":1,"m":false},{"f":0,"m":false,"v":1},{"f":0,"v":1,"m":false},{"f":0,"v":1,"m":false},{"v":1,"f":0,"m":false},{"m":false,"f":0,"v":1}],"songExportVersion":"1.0.0","songAlbum":"ANILOG Beats","lastProgramNumber":6,"songTicksPerBeat":4,"userName":"S1-PREVIEW","instruments":{"currentTime":1631889814.8223929,"userName":"S1-PREVIEW","appName":"ANILOG","appVersion":"1.1.0","patches":[{"gl":0,"patchname":"[Kick] Cheap Kick Short","o1":{"ol":1,"up":1,"hm":1,"vc":0.25,"vl":0.5,"tu":-6.9660739898681641,"nv":false,"vd":0.10000000149011612,"on":true,"gn":1.1132960319519043,"ti":-0.34756428003311157,"va":0.10000000149011612,"lw":-1,"no":0.032800234854221344,"bm":1,"cn":0.17084425687789917},"a2":{"rl":30.556486129760742,"dc":18.957450866699219,"on":true,"nv":false},"c3":{"rl":150,"su":0.80000001192092896,"dc":42.162193298339844,"on":true,"nv":false},"n1":{"rl":150,"dc":14.594589233398438,"on":true,"nv":false},"nc":7.8544173240661621,"o2":{"ol":1,"up":1,"hm":1,"vc":0.25,"vl":0.5,"tu":13,"nv":false,"vd":0.10000000149011612,"on":true,"gn":1,"ti":-0.82462853193283081,"va":0.10000000149011612,"lw":-1,"no":0.02852628193795681,"bm":1,"cn":0.25819689035415649},"a3":{"at":100,"rl":64,"su":0.5,"dc":64,"on":true,"nv":false},"gn":1.3462556600570679,"fl":1,"o3":{"up":1,"lw":-1,"on":false,"va":0.10000000149011612,"vd":0.10000000149011612,"nv":false,"ol":1,"vl":0.5,"bm":1,"hm":1,"vc":0.25},"rfi":9.9999997473787516e-06,"bank":0,"c1":{"rl":16.85627555847168,"su":-0.924896240234375,"dc":11.974584579467773,"on":true,"nv":false},"program":0,"c2":{"rl":9.8636512756347656,"dc":6.2633132934570312,"on":true,"nv":false},"a1":{"rl":9.132899284362793,"su":-0.77886021137237549,"dc":27.102611541748047,"on":true,"nv":false}},{"n1":{"rl":20000.005859375,"dc":548.62542724609375,"on":true,"nv":false},"patchname":"[Snare] Snared Short","gn":0.98749476671218872,"nc":9.2153434753417969,"c1":{"rl":150,"dc":13.914059638977051,"on":true,"nv":false},"o1":{"up":1,"vl":1,"hm":1,"tu":9.580474853515625,"nv":false,"on":true,"gn":1,"ti":-0.15837161242961884,"lw":-1,"no":0.19955518841743469,"bm":1,"ol":1},"c2":{"rl":150,"su":0.80000001192092896,"dc":400,"on":true,"nv":false},"o2":{"ol":0.23094771802425385,"up":1,"hm":1,"vl":1,"tu":15.677857398986816,"nv":false,"on":true,"gn":1,"lw":-1,"no":1,"cr":0.20842507481575012,"bm":1,"cn":0.16851857304573059},"c3":{"rl":150,"su":0.80000001192092896,"dc":400,"on":true,"nv":false},"fl":0.022084943950176239,"fli":0.00046705442946404219,"a1":{"rl":22.230808258056641,"su":-0.80960452556610107,"dc":13.724191665649414,"on":true,"nv":false},"o3":{"ol":1,"up":1,"vl":0.5,"hm":1,"vc":0.25,"nv":false,"vd":0.10000000149011612,"on":false,"va":0.10000000149011612,"lw":-1,"bm":1,"cn":0.25},"fba":0.17414127290248871,"a2":{"rl":37.37286376953125,"su":-0.39199212193489075,"dc":43.49139404296875,"on":true,"nv":false},"program":1,"rfi":0.0010000000474974513,"gl":0,"a3":{"at":100,"su":0.5,"dc":27,"on":true,"nv":false},"ni":-0.095457613468170166,"bank":0},{"gl":0,"patchname":"[Hats] Velo-Hat","fba":0.466756671667099,"o1":{"ol":0.28285256028175354,"up":1,"hm":1,"vc":0.25,"vl":0.45307439565658569,"tu":48,"nv":false,"vd":1,"on":true,"gn":11,"ti":-0.032362561672925949,"lw":-1,"no":1,"cr":0.14239487051963806,"bm":1,"cn":0.5},"a2":{"at":1.8997976779937744,"rl":6.4540300369262695,"dc":7.4913444519042969,"on":true,"nv":false},"c3":{"rl":150,"su":0.80000001192092896,"dc":400,"on":true,"nv":false},"n1":{"su":1,"rl":20000.005859375,"on":true,"nv":false},"nc":10,"o2":{"ol":0.16958385705947876,"up":1,"hm":1,"vc":0.25,"vl":0.11650487035512924,"tu":36.815540313720703,"nv":false,"vd":1,"on":true,"gn":11,"ti":-0.0088527118787169456,"lw":-1,"no":1,"bm":1,"cn":0.5},"a3":{"at":1,"rl":63.789615631103516,"su":0.5,"dc":250,"on":true,"nv":false},"gn":0.20000000298023224,"fl":-0.093602977693080902,"o3":{"up":1,"lw":-1,"on":false,"va":0.10000000149011612,"vd":0.10000000149011612,"nv":false,"ol":1,"vl":0.5,"bm":1,"hm":1,"vc":0.25},"rfi":0.0010000000474974513,"bank":0,"c1":{"rl":1215.4007568359375,"dc":3.7521328926086426,"on":true,"nv":false},"program":2,"c2":{"rl":1215.4007568359375,"dc":3.7521328926086426,"on":true,"nv":false},"a1":{"rl":11.713229179382324,"dc":5.8750553131103516,"on":true,"nv":false}},{"gl":0,"patchname":"(Untitled)","npa":0.20000000298023224,"o1":{"up":1,"vl":0.5,"hm":1,"vc":0.25,"nv":false,"vd":0.10000000149011612,"on":true,"gn":1,"va":0.10000000149011612,"lw":-1,"bm":1,"ol":1},"a2":{"at":1,"rl":150,"su":0.5,"dc":250,"on":true,"nv":false},"c3":{"rl":150,"su":0.80000001192092896,"dc":400,"on":true,"nv":false},"n1":{"rl":150,"dc":250,"on":true,"nv":false},"nc":10,"o2":{"up":1,"lw":-1,"on":false,"va":0.10000000149011612,"vd":0.10000000149011612,"nv":false,"ol":1,"vl":0.5,"bm":1,"hm":1,"vc":0.25},"a3":{"at":1,"rl":150,"su":0.5,"dc":250,"on":true,"nv":false},"gn":0.60000002384185791,"fl":100,"o3":{"up":1,"lw":-1,"on":false,"va":0.10000000149011612,"vd":0.10000000149011612,"nv":false,"ol":1,"vl":0.5,"bm":1,"hm":1,"vc":0.25},"rfi":9.9999997473787516e-06,"bank":0,"c1":{"rl":150,"su":0.80000001192092896,"dc":400,"on":true,"nv":false},"program":3,"c2":{"rl":150,"su":0.80000001192092896,"dc":400,"on":true,"nv":false},"a1":{"at":1,"rl":150,"su":0.5,"dc":250,"on":true,"nv":false}},{"gl":0,"patchname":"(Untitled)","npa":0.20000000298023224,"o1":{"up":1,"vl":0.5,"hm":1,"vc":0.25,"nv":false,"vd":0.10000000149011612,"on":true,"gn":1,"va":0.10000000149011612,"lw":-1,"bm":1,"ol":1},"a2":{"at":1,"rl":150,"su":0.5,"dc":250,"on":true,"nv":false},"c3":{"rl":150,"su":0.80000001192092896,"dc":400,"on":true,"nv":false},"n1":{"rl":150,"dc":250,"on":true,"nv":false},"nc":10,"o2":{"up":1,"lw":-1,"on":false,"va":0.10000000149011612,"vd":0.10000000149011612,"nv":false,"ol":1,"vl":0.5,"bm":1,"hm":1,"vc":0.25},"a3":{"at":1,"rl":150,"su":0.5,"dc":250,"on":true,"nv":false},"gn":0.60000002384185791,"fl":100,"o3":{"up":1,"lw":-1,"on":false,"va":0.10000000149011612,"vd":0.10000000149011612,"nv":false,"ol":1,"vl":0.5,"bm":1,"hm":1,"vc":0.25},"rfi":9.9999997473787516e-06,"bank":0,"c1":{"rl":150,"su":0.80000001192092896,"dc":400,"on":true,"nv":false},"program":4,"c2":{"rl":150,"su":0.80000001192092896,"dc":400,"on":true,"nv":false},"a1":{"at":1,"rl":150,"su":0.5,"dc":250,"on":true,"nv":false}},{"n1":{"rl":150,"dc":250,"on":true,"nv":false},"patchname":"(Untitled)","gn":0.60000002384185791,"nc":10,"c1":{"rl":150,"su":0.80000001192092896,"dc":400,"on":true,"nv":false},"o1":{"up":1,"vl":0.5,"hm":1,"vc":0.25,"nv":false,"vd":0.10000000149011612,"on":true,"gn":1,"va":0.10000000149011612,"lw":-1,"bm":1,"ol":1},"c2":{"rl":150,"su":0.80000001192092896,"dc":400,"on":true,"nv":false},"o2":{"up":1,"lw":-1,"on":false,"va":0.10000000149011612,"vd":0.10000000149011612,"nv":false,"ol":1,"vl":0.5,"bm":1,"hm":1,"vc":0.25},"c3":{"rl":150,"su":0.80000001192092896,"dc":400,"on":true,"nv":false},"fl":100,"a1":{"at":1,"rl":150,"su":0.5,"dc":250,"on":true,"nv":false},"o3":{"up":1,"lw":-1,"on":false,"va":0.10000000149011612,"vd":0.10000000149011612,"nv":false,"ol":1,"vl":0.5,"bm":1,"hm":1,"vc":0.25},"a2":{"at":1,"rl":150,"su":0.5,"dc":250,"on":true,"nv":false},"program":5,"rfi":0.00065892300335690379,"gl":0,"a3":{"at":1,"rl":150,"su":0.5,"dc":250,"on":true,"nv":false},"ni":0.26534003019332886,"npa":0.20000000298023224,"bank":0},{"n1":{"rl":150,"dc":250,"on":true,"nv":false},"patchname":"[Bass] Stereo Where-eo.","gn":0.60000002384185791,"nc":10,"afma":0.37237200140953064,"c1":{"rl":150,"su":0.80000001192092896,"dc":216.00004577636719,"on":true,"nv":false},"o1":{"up":1,"hm":1,"vc":0.15000000596046448,"vl":1,"tu":-24,"pn":-0.89999997615814209,"nv":false,"on":true,"gn":2.6286327838897705,"vd":0.10000001639127731,"lw":-1,"cr":0.012945082969963551,"bm":1,"ol":1},"c2":{"rl":150,"su":0.80000001192092896,"dc":216.00004577636719,"on":true,"nv":false},"o2":{"up":1,"hm":1,"vc":0.15000000596046448,"vl":1,"tu":-24,"pn":0.89999997615814209,"nv":false,"on":true,"gn":1.9630169868469238,"vd":0.10000001639127731,"lw":-1,"cr":0.012945082969963551,"bm":1,"ol":1},"c3":{"rl":150,"su":0.80000001192092896,"dc":400,"on":true,"nv":false},"fl":-0.80272758007049561,"a1":{"rl":125,"su":0.30000001192092896,"dc":250,"on":true,"nv":false},"o3":{"ol":1,"up":1,"hm":1,"vc":0.25,"vl":0.5,"tu":-12,"nv":false,"vd":0.10000000149011612,"on":false,"va":0.10000000149011612,"lw":-1,"bm":1,"cn":0.25},"fba":0.5,"a2":{"dl":4.9532961845397949,"rl":125,"su":0.30000001192092896,"dc":250,"on":true,"nv":false},"program":6,"rfi":0.00046947936061769724,"gl":0,"a3":{"at":100,"rl":150,"su":0.5,"dc":250,"on":true,"nv":false},"bank":0},{"gl":0,"patchname":"[Pad] String Theory.","fba":0.23088806867599487,"o1":{"ol":1,"up":1,"hm":1,"vc":0.044243998825550079,"vl":0.5,"nv":false,"vd":0.10000000149011612,"on":true,"gn":1,"va":0.79999995231628418,"lw":-1,"bm":1,"cn":0.97256654500961304},"a2":{"at":512,"rl":512,"su":0.49999991059303284,"dc":1000,"on":true,"nv":false},"c3":{"su":1,"rl":20000.005859375,"on":true,"nv":false},"n1":{"rl":150,"dc":250,"on":true,"nv":false},"nc":10,"o2":{"ol":0.78264403343200684,"up":1,"hm":1,"vc":0.022104671224951744,"vl":0.5,"tu":-0.10803604125976562,"pn":-0.5,"nv":false,"on":true,"gn":1.056761622428894,"vd":0.10000000149011612,"va":0.79999995231628418,"lw":-1,"bm":1,"cn":0.044972464442253113},"a3":{"at":512,"rl":620.01153564453125,"su":0.49999991059303284,"dc":1000,"on":true,"nv":false},"gn":0.21534685790538788,"fl":-0.35640430450439453,"o3":{"ol":0.30000001192092896,"up":1,"hm":1,"vc":0.025453595444560051,"vl":0.5,"tu":0.13334083557128906,"pn":0.60000002384185791,"nv":false,"on":true,"gn":1,"vd":0.10000000149011612,"va":0.79999995231628418,"lw":-1,"bm":1,"cn":0.9491228461265564},"rfi":0.00015676667680963874,"bank":0,"c1":{"su":1,"rl":20000.005859375,"on":true,"nv":false},"program":7,"c2":{"su":1,"rl":20000.005859375,"on":true,"nv":false},"a1":{"at":512,"rl":729,"su":0.49999991059303284,"dc":1000,"on":true,"nv":false}},{"gl":0,"patchname":"(Untitled)","npa":0.20000000298023224,"o1":{"up":1,"vl":0.5,"hm":1,"vc":0.25,"nv":false,"vd":0.10000000149011612,"on":true,"gn":1,"va":0.10000000149011612,"lw":-1,"bm":1,"ol":1},"a2":{"at":1,"rl":150,"su":0.5,"dc":250,"on":true,"nv":false},"c3":{"rl":150,"su":0.80000001192092896,"dc":400,"on":true,"nv":false},"n1":{"rl":150,"dc":250,"on":true,"nv":false},"nc":10,"o2":{"up":1,"lw":-1,"on":false,"va":0.10000000149011612,"vd":0.10000000149011612,"nv":false,"ol":1,"vl":0.5,"bm":1,"hm":1,"vc":0.25},"a3":{"at":1,"rl":150,"su":0.5,"dc":250,"on":true,"nv":false},"gn":0.60000002384185791,"fl":100,"o3":{"up":1,"lw":-1,"on":false,"va":0.10000000149011612,"vd":0.10000000149011612,"nv":false,"ol":1,"vl":0.5,"bm":1,"hm":1,"vc":0.25},"rfi":0.00041374526335857809,"bank":0,"c1":{"rl":150,"su":0.80000001192092896,"dc":400,"on":true,"nv":false},"program":8,"c2":{"rl":150,"su":0.80000001192092896,"dc":400,"on":true,"nv":false},"a1":{"at":1,"rl":150,"su":0.5,"dc":250,"on":true,"nv":false}},{"n1":{"rl":150,"dc":250,"on":true,"nv":false},"patchname":"(Untitled)","gn":0.60000002384185791,"nc":10,"c1":{"rl":150,"su":0.80000001192092896,"dc":400,"on":true,"nv":false},"o1":{"up":1,"vl":0.5,"hm":1,"vc":0.25,"nv":false,"vd":0.10000000149011612,"on":true,"gn":1,"va":0.10000000149011612,"lw":-1,"bm":1,"ol":1},"c2":{"rl":150,"su":0.80000001192092896,"dc":400,"on":true,"nv":false},"o2":{"up":1,"lw":-1,"on":false,"va":0.10000000149011612,"vd":0.10000000149011612,"nv":false,"ol":1,"vl":0.5,"bm":1,"hm":1,"vc":0.25},"c3":{"rl":150,"su":0.80000001192092896,"dc":400,"on":true,"nv":false},"fl":100,"a1":{"at":1,"rl":150,"su":0.5,"dc":250,"on":true,"nv":false},"o3":{"up":1,"lw":-1,"on":false,"va":0.10000000149011612,"vd":0.10000000149011612,"nv":false,"ol":1,"vl":0.5,"bm":1,"hm":1,"vc":0.25},"a2":{"at":1,"rl":150,"su":0.5,"dc":250,"on":true,"nv":false},"program":9,"rfi":0.00047680590068921447,"gl":0,"a3":{"at":1,"rl":150,"su":0.5,"dc":250,"on":true,"nv":false},"ni":0.26534003019332886,"npa":0.20000000298023224,"bank":0},{"gl":0,"patchname":"(Untitled)","npa":0.20000000298023224,"o1":{"up":1,"vl":0.5,"hm":1,"vc":0.25,"nv":false,"vd":0.10000000149011612,"on":true,"gn":1,"va":0.10000000149011612,"lw":-1,"bm":1,"ol":1},"a2":{"at":1,"rl":150,"su":0.5,"dc":250,"on":true,"nv":false},"c3":{"rl":150,"su":0.80000001192092896,"dc":400,"on":true,"nv":false},"n1":{"rl":150,"dc":250,"on":true,"nv":false},"nc":10,"o2":{"up":1,"lw":-1,"on":false,"va":0.10000000149011612,"vd":0.10000000149011612,"nv":false,"ol":1,"vl":0.5,"bm":1,"hm":1,"vc":0.25},"a3":{"at":1,"rl":150,"su":0.5,"dc":250,"on":true,"nv":false},"gn":0.60000002384185791,"fl":100,"o3":{"up":1,"lw":-1,"on":false,"va":0.10000000149011612,"vd":0.10000000149011612,"nv":false,"ol":1,"vl":0.5,"bm":1,"hm":1,"vc":0.25},"rfi":9.9999997473787516e-06,"bank":0,"c1":{"rl":150,"su":0.80000001192092896,"dc":400,"on":true,"nv":false},"program":10,"c2":{"rl":150,"su":0.80000001192092896,"dc":400,"on":true,"nv":false},"a1":{"at":1,"rl":150,"su":0.5,"dc":250,"on":true,"nv":false}},{"n1":{"rl":150,"dc":250,"on":true,"nv":false},"patchname":"(Untitled)","gn":0.60000002384185791,"nc":10,"c1":{"rl":150,"su":0.80000001192092896,"dc":400,"on":true,"nv":false},"o1":{"up":1,"vl":0.5,"hm":1,"vc":0.25,"nv":false,"vd":0.10000000149011612,"on":true,"gn":1,"va":0.10000000149011612,"lw":-1,"bm":1,"ol":1},"c2":{"rl":150,"su":0.80000001192092896,"dc":400,"on":true,"nv":false},"o2":{"up":1,"lw":-1,"on":false,"va":0.10000000149011612,"vd":0.10000000149011612,"nv":false,"ol":1,"vl":0.5,"bm":1,"hm":1,"vc":0.25},"c3":{"rl":150,"su":0.80000001192092896,"dc":400,"on":true,"nv":false},"fl":100,"a1":{"at":1,"rl":150,"su":0.5,"dc":250,"on":true,"nv":false},"o3":{"up":1,"lw":-1,"on":false,"va":0.10000000149011612,"vd":0.10000000149011612,"nv":false,"ol":1,"vl":0.5,"bm":1,"hm":1,"vc":0.25},"a2":{"at":1,"rl":150,"su":0.5,"dc":250,"on":true,"nv":false},"program":11,"rfi":0.00036972976522520185,"gl":0,"a3":{"at":1,"rl":150,"su":0.5,"dc":250,"on":true,"nv":false},"ni":-0.13401782512664795,"npa":0.20000000298023224,"bank":0},{"gl":0,"patchname":"(Untitled)","npa":0.20000000298023224,"o1":{"up":1,"vl":0.5,"hm":1,"vc":0.25,"nv":false,"vd":0.10000000149011612,"on":true,"gn":1,"va":0.10000000149011612,"lw":-1,"bm":1,"ol":1},"a2":{"at":1,"rl":150,"su":0.5,"dc":250,"on":true,"nv":false},"c3":{"rl":150,"su":0.80000001192092896,"dc":400,"on":true,"nv":false},"n1":{"rl":150,"dc":250,"on":true,"nv":false},"nc":10,"o2":{"up":1,"lw":-1,"on":false,"va":0.10000000149011612,"vd":0.10000000149011612,"nv":false,"ol":1,"vl":0.5,"bm":1,"hm":1,"vc":0.25},"a3":{"at":1,"rl":150,"su":0.5,"dc":250,"on":true,"nv":false},"gn":0.60000002384185791,"fl":100,"o3":{"up":1,"lw":-1,"on":false,"va":0.10000000149011612,"vd":0.10000000149011612,"nv":false,"ol":1,"vl":0.5,"bm":1,"hm":1,"vc":0.25},"rfi":9.9999997473787516e-06,"bank":0,"c1":{"rl":150,"su":0.80000001192092896,"dc":400,"on":true,"nv":false},"program":12,"c2":{"rl":150,"su":0.80000001192092896,"dc":400,"on":true,"nv":false},"a1":{"at":1,"rl":150,"su":0.5,"dc":250,"on":true,"nv":false}},{"gl":0,"patchname":"(Untitled)","npa":0.20000000298023224,"o1":{"up":1,"vl":0.5,"hm":1,"vc":0.25,"nv":false,"vd":0.10000000149011612,"on":true,"gn":1,"va":0.10000000149011612,"lw":-1,"bm":1,"ol":1},"a2":{"at":1,"rl":150,"su":0.5,"dc":250,"on":true,"nv":false},"c3":{"rl":150,"su":0.80000001192092896,"dc":400,"on":true,"nv":false},"n1":{"rl":150,"dc":250,"on":true,"nv":false},"nc":10,"o2":{"up":1,"lw":-1,"on":false,"va":0.10000000149011612,"vd":0.10000000149011612,"nv":false,"ol":1,"vl":0.5,"bm":1,"hm":1,"vc":0.25},"a3":{"at":1,"rl":150,"su":0.5,"dc":250,"on":true,"nv":false},"gn":0.60000002384185791,"fl":100,"o3":{"up":1,"lw":-1,"on":false,"va":0.10000000149011612,"vd":0.10000000149011612,"nv":false,"ol":1,"vl":0.5,"bm":1,"hm":1,"vc":0.25},"rfi":0.00020246196072548628,"bank":0,"c1":{"rl":150,"su":0.80000001192092896,"dc":400,"on":true,"nv":false},"program":13,"c2":{"rl":150,"su":0.80000001192092896,"dc":400,"on":true,"nv":false},"a1":{"at":1,"rl":150,"su":0.5,"dc":250,"on":true,"nv":false}},{"gl":0,"patchname":"(Untitled)","npa":0.20000000298023224,"o1":{"up":1,"vl":0.5,"hm":1,"vc":0.25,"nv":false,"vd":0.10000000149011612,"on":true,"gn":1,"va":0.10000000149011612,"lw":-1,"bm":1,"ol":1},"a2":{"at":1,"rl":150,"su":0.5,"dc":250,"on":true,"nv":false},"c3":{"rl":150,"su":0.80000001192092896,"dc":400,"on":true,"nv":false},"n1":{"rl":150,"dc":250,"on":true,"nv":false},"nc":10,"o2":{"up":1,"lw":-1,"on":false,"va":0.10000000149011612,"vd":0.10000000149011612,"nv":false,"ol":1,"vl":0.5,"bm":1,"hm":1,"vc":0.25},"a3":{"at":1,"rl":150,"su":0.5,"dc":250,"on":true,"nv":false},"gn":0.60000002384185791,"fl":100,"o3":{"up":1,"lw":-1,"on":false,"va":0.10000000149011612,"vd":0.10000000149011612,"nv":false,"ol":1,"vl":0.5,"bm":1,"hm":1,"vc":0.25},"rfi":0.00078766088699921966,"bank":0,"c1":{"rl":150,"su":0.80000001192092896,"dc":400,"on":true,"nv":false},"program":14,"c2":{"rl":150,"su":0.80000001192092896,"dc":400,"on":true,"nv":false},"a1":{"at":1,"rl":150,"su":0.5,"dc":250,"on":true,"nv":false}},{"gl":0,"patchname":"(Untitled)","npa":0.20000000298023224,"o1":{"up":1,"vl":0.5,"hm":1,"vc":0.25,"nv":false,"vd":0.10000000149011612,"on":true,"gn":1,"va":0.10000000149011612,"lw":-1,"bm":1,"ol":1},"a2":{"at":1,"rl":150,"su":0.5,"dc":250,"on":true,"nv":false},"c3":{"rl":150,"su":0.80000001192092896,"dc":400,"on":true,"nv":false},"n1":{"rl":150,"dc":250,"on":true,"nv":false},"nc":10,"o2":{"up":1,"lw":-1,"on":false,"va":0.10000000149011612,"vd":0.10000000149011612,"nv":false,"ol":1,"vl":0.5,"bm":1,"hm":1,"vc":0.25},"a3":{"at":1,"rl":150,"su":0.5,"dc":250,"on":true,"nv":false},"gn":0.60000002384185791,"fl":100,"o3":{"up":1,"lw":-1,"on":false,"va":0.10000000149011612,"vd":0.10000000149011612,"nv":false,"ol":1,"vl":0.5,"bm":1,"hm":1,"vc":0.25},"rfi":0.00078766088699921966,"bank":0,"c1":{"rl":150,"su":0.80000001192092896,"dc":400,"on":true,"nv":false},"program":15,"c2":{"rl":150,"su":0.80000001192092896,"dc":400,"on":true,"nv":false},"a1":{"at":1,"rl":150,"su":0.5,"dc":250,"on":true,"nv":false}},{"gl":0,"patchname":"(Untitled)","npa":0.20000000298023224,"o1":{"up":1,"vl":0.5,"hm":1,"vc":0.25,"nv":false,"vd":0.10000000149011612,"on":true,"gn":1,"va":0.10000000149011612,"lw":-1,"bm":1,"ol":1},"a2":{"at":1,"rl":150,"su":0.5,"dc":250,"on":true,"nv":false},"c3":{"rl":150,"su":0.80000001192092896,"dc":400,"on":true,"nv":false},"n1":{"rl":150,"dc":250,"on":true,"nv":false},"nc":10,"o2":{"up":1,"lw":-1,"on":false,"va":0.10000000149011612,"vd":0.10000000149011612,"nv":false,"ol":1,"vl":0.5,"bm":1,"hm":1,"vc":0.25},"a3":{"at":1,"rl":150,"su":0.5,"dc":250,"on":true,"nv":false},"gn":0.60000002384185791,"fl":100,"o3":{"up":1,"lw":-1,"on":false,"va":0.10000000149011612,"vd":0.10000000149011612,"nv":false,"ol":1,"vl":0.5,"bm":1,"hm":1,"vc":0.25},"rfi":9.9999997473787516e-06,"bank":0,"c1":{"rl":150,"su":0.80000001192092896,"dc":400,"on":true,"nv":false},"program":16,"c2":{"rl":150,"su":0.80000001192092896,"dc":400,"on":true,"nv":false},"a1":{"at":1,"rl":150,"su":0.5,"dc":250,"on":true,"nv":false}},{"gl":0,"patchname":"(Untitled)","npa":0.20000000298023224,"o1":{"up":1,"vl":0.5,"hm":1,"vc":0.25,"nv":false,"vd":0.10000000149011612,"on":true,"gn":1,"va":0.10000000149011612,"lw":-1,"bm":1,"ol":1},"a2":{"at":1,"rl":150,"su":0.5,"dc":250,"on":true,"nv":false},"c3":{"rl":150,"su":0.80000001192092896,"dc":400,"on":true,"nv":false},"n1":{"rl":150,"dc":250,"on":true,"nv":false},"nc":10,"o2":{"up":1,"lw":-1,"on":false,"va":0.10000000149011612,"vd":0.10000000149011612,"nv":false,"ol":1,"vl":0.5,"bm":1,"hm":1,"vc":0.25},"a3":{"at":1,"rl":150,"su":0.5,"dc":250,"on":true,"nv":false},"gn":0.60000002384185791,"fl":100,"o3":{"up":1,"lw":-1,"on":false,"va":0.10000000149011612,"vd":0.10000000149011612,"nv":false,"ol":1,"vl":0.5,"bm":1,"hm":1,"vc":0.25},"rfi":0.00041374526335857809,"bank":0,"c1":{"rl":150,"su":0.80000001192092896,"dc":400,"on":true,"nv":false},"program":17,"c2":{"rl":150,"su":0.80000001192092896,"dc":400,"on":true,"nv":false},"a1":{"at":1,"rl":150,"su":0.5,"dc":250,"on":true,"nv":false}},{"gl":0,"patchname":"(Untitled)","npa":0.20000000298023224,"o1":{"up":1,"vl":0.5,"hm":1,"vc":0.25,"nv":false,"vd":0.10000000149011612,"on":true,"gn":1,"va":0.10000000149011612,"lw":-1,"bm":1,"ol":1},"a2":{"at":1,"rl":150,"su":0.5,"dc":250,"on":true,"nv":false},"c3":{"rl":150,"su":0.80000001192092896,"dc":400,"on":true,"nv":false},"n1":{"rl":150,"dc":250,"on":true,"nv":false},"nc":10,"o2":{"up":1,"lw":-1,"on":false,"va":0.10000000149011612,"vd":0.10000000149011612,"nv":false,"ol":1,"vl":0.5,"bm":1,"hm":1,"vc":0.25},"a3":{"at":1,"rl":150,"su":0.5,"dc":250,"on":true,"nv":false},"gn":0.60000002384185791,"fl":100,"o3":{"up":1,"lw":-1,"on":false,"va":0.10000000149011612,"vd":0.10000000149011612,"nv":false,"ol":1,"vl":0.5,"bm":1,"hm":1,"vc":0.25},"rfi":9.9999997473787516e-06,"bank":0,"c1":{"rl":150,"su":0.80000001192092896,"dc":400,"on":true,"nv":false},"program":18,"c2":{"rl":150,"su":0.80000001192092896,"dc":400,"on":true,"nv":false},"a1":{"at":1,"rl":150,"su":0.5,"dc":250,"on":true,"nv":false}},{"gl":0,"patchname":"(Untitled)","npa":0.20000000298023224,"o1":{"up":1,"vl":0.5,"hm":1,"vc":0.25,"nv":false,"vd":0.10000000149011612,"on":true,"gn":1,"va":0.10000000149011612,"lw":-1,"bm":1,"ol":1},"a2":{"at":1,"rl":150,"su":0.5,"dc":250,"on":true,"nv":false},"c3":{"rl":150,"su":0.80000001192092896,"dc":400,"on":true,"nv":false},"n1":{"rl":150,"dc":250,"on":true,"nv":false},"nc":10,"o2":{"up":1,"lw":-1,"on":false,"va":0.10000000149011612,"vd":0.10000000149011612,"nv":false,"ol":1,"vl":0.5,"bm":1,"hm":1,"vc":0.25},"a3":{"at":1,"rl":150,"su":0.5,"dc":250,"on":true,"nv":false},"gn":0.60000002384185791,"fl":100,"o3":{"up":1,"lw":-1,"on":false,"va":0.10000000149011612,"vd":0.10000000149011612,"nv":false,"ol":1,"vl":0.5,"bm":1,"hm":1,"vc":0.25},"rfi":9.9999997473787516e-06,"bank":0,"c1":{"rl":150,"su":0.80000001192092896,"dc":400,"on":true,"nv":false},"program":19,"c2":{"rl":150,"su":0.80000001192092896,"dc":400,"on":true,"nv":false},"a1":{"at":1,"rl":150,"su":0.5,"dc":250,"on":true,"nv":false}},{"gl":0,"patchname":"(Untitled)","npa":0.20000000298023224,"o1":{"up":1,"vl":0.5,"hm":1,"vc":0.25,"nv":false,"vd":0.10000000149011612,"on":true,"gn":1,"va":0.10000000149011612,"lw":-1,"bm":1,"ol":1},"a2":{"at":1,"rl":150,"su":0.5,"dc":250,"on":true,"nv":false},"c3":{"rl":150,"su":0.80000001192092896,"dc":400,"on":true,"nv":false},"n1":{"rl":150,"dc":250,"on":true,"nv":false},"nc":10,"o2":{"up":1,"lw":-1,"on":false,"va":0.10000000149011612,"vd":0.10000000149011612,"nv":false,"ol":1,"vl":0.5,"bm":1,"hm":1,"vc":0.25},"a3":{"at":1,"rl":150,"su":0.5,"dc":250,"on":true,"nv":false},"gn":0.60000002384185791,"fl":100,"o3":{"up":1,"lw":-1,"on":false,"va":0.10000000149011612,"vd":0.10000000149011612,"nv":false,"ol":1,"vl":0.5,"bm":1,"hm":1,"vc":0.25},"rfi":4.9999998736893758e-05,"bank":0,"c1":{"rl":150,"su":0.80000001192092896,"dc":400,"on":true,"nv":false},"program":20,"c2":{"rl":150,"su":0.80000001192092896,"dc":400,"on":true,"nv":false},"a1":{"at":1,"rl":150,"su":0.5,"dc":250,"on":true,"nv":false}},{"gl":0,"patchname":"(Untitled)","npa":0.20000000298023224,"o1":{"up":1,"vl":0.5,"hm":1,"vc":0.25,"nv":false,"vd":0.10000000149011612,"on":true,"gn":1,"va":0.10000000149011612,"lw":-1,"bm":1,"ol":1},"a2":{"at":1,"rl":150,"su":0.5,"dc":250,"on":true,"nv":false},"c3":{"rl":150,"su":0.80000001192092896,"dc":400,"on":true,"nv":false},"n1":{"rl":150,"dc":250,"on":true,"nv":false},"nc":10,"o2":{"up":1,"lw":-1,"on":false,"va":0.10000000149011612,"vd":0.10000000149011612,"nv":false,"ol":1,"vl":0.5,"bm":1,"hm":1,"vc":0.25},"a3":{"at":1,"rl":150,"su":0.5,"dc":250,"on":true,"nv":false},"gn":0.60000002384185791,"fl":100,"o3":{"up":1,"lw":-1,"on":false,"va":0.10000000149011612,"vd":0.10000000149011612,"nv":false,"ol":1,"vl":0.5,"bm":1,"hm":1,"vc":0.25},"rfi":9.9999997473787516e-06,"bank":0,"c1":{"rl":150,"su":0.80000001192092896,"dc":400,"on":true,"nv":false},"program":21,"c2":{"rl":150,"su":0.80000001192092896,"dc":400,"on":true,"nv":false},"a1":{"at":1,"rl":150,"su":0.5,"dc":250,"on":true,"nv":false}},{"gl":0,"patchname":"(Untitled)","npa":0.20000000298023224,"o1":{"up":1,"vl":0.5,"hm":1,"vc":0.25,"nv":false,"vd":0.10000000149011612,"on":true,"gn":1,"va":0.10000000149011612,"lw":-1,"bm":1,"ol":1},"a2":{"at":1,"rl":150,"su":0.5,"dc":250,"on":true,"nv":false},"c3":{"rl":150,"su":0.80000001192092896,"dc":400,"on":true,"nv":false},"n1":{"rl":150,"dc":250,"on":true,"nv":false},"nc":10,"o2":{"up":1,"lw":-1,"on":false,"va":0.10000000149011612,"vd":0.10000000149011612,"nv":false,"ol":1,"vl":0.5,"bm":1,"hm":1,"vc":0.25},"a3":{"at":1,"rl":150,"su":0.5,"dc":250,"on":true,"nv":false},"gn":0.60000002384185791,"fl":100,"o3":{"up":1,"lw":-1,"on":false,"va":0.10000000149011612,"vd":0.10000000149011612,"nv":false,"ol":1,"vl":0.5,"bm":1,"hm":1,"vc":0.25},"rfi":0.00067438645055517554,"bank":0,"c1":{"rl":150,"su":0.80000001192092896,"dc":400,"on":true,"nv":false},"program":22,"c2":{"rl":150,"su":0.80000001192092896,"dc":400,"on":true,"nv":false},"a1":{"at":1,"rl":150,"su":0.5,"dc":250,"on":true,"nv":false}},{"gl":0,"patchname":"(Untitled)","npa":0.20000000298023224,"o1":{"up":1,"vl":0.5,"hm":1,"vc":0.25,"nv":false,"vd":0.10000000149011612,"on":true,"gn":1,"va":0.10000000149011612,"lw":-1,"bm":1,"ol":1},"a2":{"at":1,"rl":150,"su":0.5,"dc":250,"on":true,"nv":false},"c3":{"rl":150,"su":0.80000001192092896,"dc":400,"on":true,"nv":false},"n1":{"rl":150,"dc":250,"on":true,"nv":false},"nc":10,"o2":{"up":1,"lw":-1,"on":false,"va":0.10000000149011612,"vd":0.10000000149011612,"nv":false,"ol":1,"vl":0.5,"bm":1,"hm":1,"vc":0.25},"a3":{"at":1,"rl":150,"su":0.5,"dc":250,"on":true,"nv":false},"gn":0.60000002384185791,"fl":100,"o3":{"up":1,"lw":-1,"on":false,"va":0.10000000149011612,"vd":0.10000000149011612,"nv":false,"ol":1,"vl":0.5,"bm":1,"hm":1,"vc":0.25},"rfi":9.9999997473787516e-06,"bank":0,"c1":{"rl":150,"su":0.80000001192092896,"dc":400,"on":true,"nv":false},"program":23,"c2":{"rl":150,"su":0.80000001192092896,"dc":400,"on":true,"nv":false},"a1":{"at":1,"rl":150,"su":0.5,"dc":250,"on":true,"nv":false}},{"gl":0,"patchname":"(Untitled)","npa":0.20000000298023224,"o1":{"up":1,"vl":0.5,"hm":1,"vc":0.25,"nv":false,"vd":0.10000000149011612,"on":true,"gn":1,"va":0.10000000149011612,"lw":-1,"bm":1,"ol":1},"a2":{"at":1,"rl":150,"su":0.5,"dc":250,"on":true,"nv":false},"c3":{"rl":150,"su":0.80000001192092896,"dc":400,"on":true,"nv":false},"n1":{"rl":150,"dc":250,"on":true,"nv":false},"nc":10,"o2":{"up":1,"lw":-1,"on":false,"va":0.10000000149011612,"vd":0.10000000149011612,"nv":false,"ol":1,"vl":0.5,"bm":1,"hm":1,"vc":0.25},"a3":{"at":1,"rl":150,"su":0.5,"dc":250,"on":true,"nv":false},"gn":0.60000002384185791,"fl":100,"o3":{"up":1,"lw":-1,"on":false,"va":0.10000000149011612,"vd":0.10000000149011612,"nv":false,"ol":1,"vl":0.5,"bm":1,"hm":1,"vc":0.25},"rfi":9.9999997473787516e-06,"bank":0,"c1":{"rl":150,"su":0.80000001192092896,"dc":400,"on":true,"nv":false},"program":24,"c2":{"rl":150,"su":0.80000001192092896,"dc":400,"on":true,"nv":false},"a1":{"at":1,"rl":150,"su":0.5,"dc":250,"on":true,"nv":false}},{"gl":0,"patchname":"(Untitled)","npa":0.20000000298023224,"o1":{"up":1,"vl":0.5,"hm":1,"vc":0.25,"nv":false,"vd":0.10000000149011612,"on":true,"gn":1,"va":0.10000000149011612,"lw":-1,"bm":1,"ol":1},"a2":{"at":1,"rl":150,"su":0.5,"dc":250,"on":true,"nv":false},"c3":{"rl":150,"su":0.80000001192092896,"dc":400,"on":true,"nv":false},"n1":{"rl":150,"dc":250,"on":true,"nv":false},"nc":10,"o2":{"up":1,"lw":-1,"on":false,"va":0.10000000149011612,"vd":0.10000000149011612,"nv":false,"ol":1,"vl":0.5,"bm":1,"hm":1,"vc":0.25},"a3":{"at":1,"rl":150,"su":0.5,"dc":250,"on":true,"nv":false},"gn":0.60000002384185791,"fl":100,"o3":{"up":1,"lw":-1,"on":false,"va":0.10000000149011612,"vd":0.10000000149011612,"nv":false,"ol":1,"vl":0.5,"bm":1,"hm":1,"vc":0.25},"rfi":9.9999997473787516e-06,"bank":0,"c1":{"rl":150,"su":0.80000001192092896,"dc":400,"on":true,"nv":false},"program":25,"c2":{"rl":150,"su":0.80000001192092896,"dc":400,"on":true,"nv":false},"a1":{"at":1,"rl":150,"su":0.5,"dc":250,"on":true,"nv":false}},{"gl":0,"patchname":"(Untitled)","npa":0.20000000298023224,"o1":{"up":1,"vl":0.5,"hm":1,"vc":0.25,"nv":false,"vd":0.10000000149011612,"on":true,"gn":1,"va":0.10000000149011612,"lw":-1,"bm":1,"ol":1},"a2":{"at":1,"rl":150,"su":0.5,"dc":250,"on":true,"nv":false},"c3":{"rl":150,"su":0.80000001192092896,"dc":400,"on":true,"nv":false},"n1":{"rl":150,"dc":250,"on":true,"nv":false},"nc":10,"o2":{"up":1,"lw":-1,"on":false,"va":0.10000000149011612,"vd":0.10000000149011612,"nv":false,"ol":1,"vl":0.5,"bm":1,"hm":1,"vc":0.25},"a3":{"at":1,"rl":150,"su":0.5,"dc":250,"on":true,"nv":false},"gn":0.60000002384185791,"fl":100,"o3":{"up":1,"lw":-1,"on":false,"va":0.10000000149011612,"vd":0.10000000149011612,"nv":false,"ol":1,"vl":0.5,"bm":1,"hm":1,"vc":0.25},"rfi":9.9999997473787516e-06,"bank":0,"c1":{"rl":150,"su":0.80000001192092896,"dc":400,"on":true,"nv":false},"program":26,"c2":{"rl":150,"su":0.80000001192092896,"dc":400,"on":true,"nv":false},"a1":{"at":1,"rl":150,"su":0.5,"dc":250,"on":true,"nv":false}},{"gl":0,"patchname":"(Untitled)","npa":0.20000000298023224,"o1":{"up":1,"vl":0.5,"hm":1,"vc":0.25,"nv":false,"vd":0.10000000149011612,"on":true,"gn":1,"va":0.10000000149011612,"lw":-1,"bm":1,"ol":1},"a2":{"at":1,"rl":150,"su":0.5,"dc":250,"on":true,"nv":false},"c3":{"rl":150,"su":0.80000001192092896,"dc":400,"on":true,"nv":false},"n1":{"rl":150,"dc":250,"on":true,"nv":false},"nc":10,"o2":{"up":1,"lw":-1,"on":false,"va":0.10000000149011612,"vd":0.10000000149011612,"nv":false,"ol":1,"vl":0.5,"bm":1,"hm":1,"vc":0.25},"a3":{"at":1,"rl":150,"su":0.5,"dc":250,"on":true,"nv":false},"gn":0.60000002384185791,"fl":100,"o3":{"up":1,"lw":-1,"on":false,"va":0.10000000149011612,"vd":0.10000000149011612,"nv":false,"ol":1,"vl":0.5,"bm":1,"hm":1,"vc":0.25},"rfi":0.00022456324950326234,"bank":0,"c1":{"rl":150,"su":0.80000001192092896,"dc":400,"on":true,"nv":false},"program":27,"c2":{"rl":150,"su":0.80000001192092896,"dc":400,"on":true,"nv":false},"a1":{"at":1,"rl":150,"su":0.5,"dc":250,"on":true,"nv":false}},{"gl":0,"patchname":"(Untitled)","npa":0.20000000298023224,"o1":{"up":1,"vl":0.5,"hm":1,"vc":0.25,"nv":false,"vd":0.10000000149011612,"on":true,"gn":1,"va":0.10000000149011612,"lw":-1,"bm":1,"ol":1},"a2":{"at":1,"rl":150,"su":0.5,"dc":250,"on":true,"nv":false},"c3":{"rl":150,"su":0.80000001192092896,"dc":400,"on":true,"nv":false},"n1":{"rl":150,"dc":250,"on":true,"nv":false},"nc":10,"o2":{"up":1,"lw":-1,"on":false,"va":0.10000000149011612,"vd":0.10000000149011612,"nv":false,"ol":1,"vl":0.5,"bm":1,"hm":1,"vc":0.25},"a3":{"at":1,"rl":150,"su":0.5,"dc":250,"on":true,"nv":false},"gn":0.60000002384185791,"fl":100,"o3":{"up":1,"lw":-1,"on":false,"va":0.10000000149011612,"vd":0.10000000149011612,"nv":false,"ol":1,"vl":0.5,"bm":1,"hm":1,"vc":0.25},"rfi":0.00076097133569419384,"bank":0,"c1":{"rl":150,"su":0.80000001192092896,"dc":400,"on":true,"nv":false},"program":28,"c2":{"rl":150,"su":0.80000001192092896,"dc":400,"on":true,"nv":false},"a1":{"at":1,"rl":150,"su":0.5,"dc":250,"on":true,"nv":false}},{"gl":0,"patchname":"(Untitled)","npa":0.20000000298023224,"o1":{"up":1,"vl":0.5,"hm":1,"vc":0.25,"nv":false,"vd":0.10000000149011612,"on":true,"gn":1,"va":0.10000000149011612,"lw":-1,"bm":1,"ol":1},"a2":{"at":1,"rl":150,"su":0.5,"dc":250,"on":true,"nv":false},"c3":{"rl":150,"su":0.80000001192092896,"dc":400,"on":true,"nv":false},"n1":{"rl":150,"dc":250,"on":true,"nv":false},"nc":10,"o2":{"up":1,"lw":-1,"on":false,"va":0.10000000149011612,"vd":0.10000000149011612,"nv":false,"ol":1,"vl":0.5,"bm":1,"hm":1,"vc":0.25},"a3":{"at":1,"rl":150,"su":0.5,"dc":250,"on":true,"nv":false},"gn":0.60000002384185791,"fl":100,"o3":{"up":1,"lw":-1,"on":false,"va":0.10000000149011612,"vd":0.10000000149011612,"nv":false,"ol":1,"vl":0.5,"bm":1,"hm":1,"vc":0.25},"rfi":6.0983304138062522e-05,"bank":0,"c1":{"rl":150,"su":0.80000001192092896,"dc":400,"on":true,"nv":false},"program":29,"c2":{"rl":150,"su":0.80000001192092896,"dc":400,"on":true,"nv":false},"a1":{"at":1,"rl":150,"su":0.5,"dc":250,"on":true,"nv":false}},{"gl":0,"patchname":"(Untitled)","npa":0.20000000298023224,"o1":{"up":1,"vl":0.5,"hm":1,"vc":0.25,"nv":false,"vd":0.10000000149011612,"on":true,"gn":1,"va":0.10000000149011612,"lw":-1,"bm":1,"ol":1},"a2":{"at":1,"rl":150,"su":0.5,"dc":250,"on":true,"nv":false},"c3":{"rl":150,"su":0.80000001192092896,"dc":400,"on":true,"nv":false},"n1":{"rl":150,"dc":250,"on":true,"nv":false},"nc":10,"o2":{"up":1,"lw":-1,"on":false,"va":0.10000000149011612,"vd":0.10000000149011612,"nv":false,"ol":1,"vl":0.5,"bm":1,"hm":1,"vc":0.25},"a3":{"at":1,"rl":150,"su":0.5,"dc":250,"on":true,"nv":false},"gn":0.60000002384185791,"fl":100,"o3":{"up":1,"lw":-1,"on":false,"va":0.10000000149011612,"vd":0.10000000149011612,"nv":false,"ol":1,"vl":0.5,"bm":1,"hm":1,"vc":0.25},"rfi":2.3606447939528152e-05,"bank":0,"c1":{"rl":150,"su":0.80000001192092896,"dc":400,"on":true,"nv":false},"program":30,"c2":{"rl":150,"su":0.80000001192092896,"dc":400,"on":true,"nv":false},"a1":{"at":1,"rl":150,"su":0.5,"dc":250,"on":true,"nv":false}},{"n1":{"rl":150,"dc":250,"on":true,"nv":false},"patchname":"(Untitled)","gn":0.60000002384185791,"nc":10,"c1":{"rl":150,"su":0.80000001192092896,"dc":400,"on":true,"nv":false},"o1":{"up":1,"vl":0.5,"hm":1,"vc":0.25,"nv":false,"vd":0.10000000149011612,"on":true,"gn":1,"va":0.10000000149011612,"lw":-1,"bm":1,"ol":1},"c2":{"rl":150,"su":0.80000001192092896,"dc":400,"on":true,"nv":false},"o2":{"up":1,"lw":-1,"on":false,"va":0.10000000149011612,"vd":0.10000000149011612,"nv":false,"ol":1,"vl":0.5,"bm":1,"hm":1,"vc":0.25},"c3":{"rl":150,"su":0.80000001192092896,"dc":400,"on":true,"nv":false},"fl":100,"a1":{"at":1,"rl":150,"su":0.5,"dc":250,"on":true,"nv":false},"o3":{"up":1,"lw":-1,"on":false,"va":0.10000000149011612,"vd":0.10000000149011612,"nv":false,"ol":1,"vl":0.5,"bm":1,"hm":1,"vc":0.25},"a2":{"at":1,"rl":150,"su":0.5,"dc":250,"on":true,"nv":false},"program":31,"rfi":9.9999997473787516e-06,"gl":0,"a3":{"at":1,"rl":150,"su":0.5,"dc":250,"on":true,"nv":false},"ni":0.12944965064525604,"npa":0.20000000298023224,"bank":0}],"version":2678},"isUsingSharpNotes":false}